satex.py
setup.py