Metadata-Version: 1.0
Name: satex
Version: 1.2.1
Summary: Helper script for managing SAT Heritage docker images
Home-page: https://github.com/sat-heritage/docker-images
Author: Loïc Paulevé
Author-email: loic.pauleve@labri.fr
License: UNKNOWN
Platform: UNKNOWN
